monkeysign/__init__.py
monkeysign/_version.py
monkeysign/build_manpage.py
monkeysign/cli.py
monkeysign/documentation.py
monkeysign/gpg.py
monkeysign/gtkui.py
monkeysign/msg_exception.py
monkeysign/msgfmt.py
monkeysign/translation.py
monkeysign/ui.py
monkeysign/po/cs/LC_MESSAGES/monkeysign.mo
monkeysign/po/es/LC_MESSAGES/monkeysign.mo
monkeysign/po/fr/LC_MESSAGES/monkeysign.mo
monkeysign/po/it/LC_MESSAGES/monkeysign.mo
monkeysign/po/ru/LC_MESSAGES/monkeysign.mo
monkeysign/tests/__init__.py
monkeysign/tests/mua-writer.py
monkeysign/tests/test_gpg.py
monkeysign/tests/test_lib.py
monkeysign/tests/test_network.py
monkeysign/tests/test_ui.py
monkeysign/tests/files/323F39BD-secret.asc
monkeysign/tests/files/323F39BD.asc
monkeysign/tests/files/576407A629299233.asc
monkeysign/tests/files/6D866396.asc
monkeysign/tests/files/7B75921E.asc
monkeysign/tests/files/96F47C6A-revoke.asc
monkeysign/tests/files/96F47C6A-revuid.asc
monkeysign/tests/files/96F47C6A-secret.asc
monkeysign/tests/files/96F47C6A.asc
monkeysign/tests/files/96F47C6A.png
monkeysign/tests/files/ECAA37C45C7E48CE.asc
monkeysign/tests/files/README
monkeysign/tests/files/testfile.txt
monkeysign/tests/files/testfile.txt.asc
monkeysign-2.2.4.data/data/share/icons/hicolor/scalable/logo.simple.svg
monkeysign-2.2.4.data/data/share/man/man1/monkeysign.1
monkeysign-2.2.4.data/data/share/pixmaps/logo.simple.png
monkeysign-2.2.4.data/scripts/monkeyscan
monkeysign-2.2.4.data/scripts/monkeysign
monkeysign-2.2.4.dist-info/DESCRIPTION.rst
monkeysign-2.2.4.dist-info/METADATA
monkeysign-2.2.4.dist-info/RECORD
monkeysign-2.2.4.dist-info/WHEEL
monkeysign-2.2.4.dist-info/metadata.json
monkeysign-2.2.4.dist-info/top_level.txt
