Metadata-Version: 2.0
Name: monkeysign
Version: 2.2.4
Summary: OpenPGP key exchange for humans
Home-page: http://web.monkeysphere.info/monkeysign
Author: Antoine Beaupré
Author-email: anarcat@debian.org
License: UNKNOWN
Platform: UNKNOWN
Classifier: Development Status :: 5 - Production/Stable
Classifier: Intended Audience :: Developers
Classifier: Intended Audience :: System Administrators
Classifier: Intended Audience :: End Users/Desktop
Classifier: Intended Audience :: Information Technology
Classifier: Intended Audience :: Legal Industry
Classifier: Intended Audience :: Telecommunications Industry
Classifier: License :: OSI Approved :: GNU General Public License v3 or later (GPLv3+)
Classifier: Programming Language :: Python
Classifier: Programming Language :: Python :: 2
Classifier: Programming Language :: Python :: 2.4
Classifier: Programming Language :: Python :: 2.5
Classifier: Programming Language :: Python :: 2.6
Classifier: Programming Language :: Python :: 2.7
Classifier: Operating System :: OS Independent
Classifier: Environment :: X11 Applications :: GTK
Classifier: Environment :: Console
Classifier: Natural Language :: English
Classifier: Natural Language :: French
Classifier: Natural Language :: Italian
Classifier: Natural Language :: Spanish
Classifier: Topic :: Communications :: Email
Classifier: Topic :: Multimedia :: Video :: Capture
Classifier: Topic :: Security :: Cryptography
Classifier: Topic :: Software Development :: Libraries :: Python Modules
Requires-Dist: pysocks
